{
    "code": "190230",
    "data": [
        {
            "baseYr": "2018",
            "mticd": null,
            "itcNatCd": null,
            "natName": null,
            "impAmt": null,
            "expAmt": null,
            "korImpAmt": null,
            "korExpAmt": null,
            "korImpMkshRate": null,
            "impMkshRate": null,
            "impGrowthRate": null,
            "expMkshRate": null,
            "expGrowthRate": null,
            "impMkshRateChngVal": null,
            "impGrowthRateChngVal": null,
            "yr2GrowthRate": null,
            "yr5GrowthRate": null,
            "expEntpCnt": null,
            "impCntryCnt": null,
            "buyerCnt": null,
            "byoffrCnt": null,
            "dataRegDt": null,
            "hscd": null,
            "cmdltNm": null,
            "cmdltParentNm": null,
            "cmdltGrParentNm": null,
            "quCd": null,
            "rank": null,
            "tradeBal": null,
            "baseYm": null,
            "tradeType": null,
            "predRank": null,
            "avgTarifRate": null,
            "korExpsttAmt": null,
            "korExpsttTotalAmt": 477081291.0,
            "popltnVal": null,
            "gdpVal": null,
            "isoWd2NatCd": null,
            "kcskorImpAmt": null,
            "predAmt": null,
            "resnCnt": null
        },
        {
            "baseYr": "2019",
            "mticd": null,
            "itcNatCd": null,
            "natName": null,
            "impAmt": null,
            "expAmt": null,
            "korImpAmt": null,
            "korExpAmt": null,
            "korImpMkshRate": null,
            "impMkshRate": null,
            "impGrowthRate": null,
            "expMkshRate": null,
            "expGrowthRate": null,
            "impMkshRateChngVal": null,
            "impGrowthRateChngVal": null,
            "yr2GrowthRate": null,
            "yr5GrowthRate": null,
            "expEntpCnt": null,
            "impCntryCnt": null,
            "buyerCnt": null,
            "byoffrCnt": null,
            "dataRegDt": null,
            "hscd": null,
            "cmdltNm": null,
            "cmdltParentNm": null,
            "cmdltGrParentNm": null,
            "quCd": null,
            "rank": null,
            "tradeBal": null,
            "baseYm": null,
            "tradeType": null,
            "predRank": null,
            "avgTarifRate": null,
            "korExpsttAmt": null,
            "korExpsttTotalAmt": 548941044.0,
            "popltnVal": null,
            "gdpVal": null,
            "isoWd2NatCd": null,
            "kcskorImpAmt": null,
            "predAmt": null,
            "resnCnt": null
        },
        {
            "baseYr": "2020",
            "mticd": null,
            "itcNatCd": null,
            "natName": null,
            "impAmt": null,
            "expAmt": null,
            "korImpAmt": null,
            "korExpAmt": null,
            "korImpMkshRate": null,
            "impMkshRate": null,
            "impGrowthRate": null,
            "expMkshRate": null,
            "expGrowthRate": null,
            "impMkshRateChngVal": null,
            "impGrowthRateChngVal": null,
            "yr2GrowthRate": null,
            "yr5GrowthRate": null,
            "expEntpCnt": null,
            "impCntryCnt": null,
            "buyerCnt": null,
            "byoffrCnt": null,
            "dataRegDt": null,
            "hscd": null,
            "cmdltNm": null,
            "cmdltParentNm": null,
            "cmdltGrParentNm": null,
            "quCd": null,
            "rank": null,
            "tradeBal": null,
            "baseYm": null,
            "tradeType": null,
            "predRank": null,
            "avgTarifRate": null,
            "korExpsttAmt": null,
            "korExpsttTotalAmt": 686126331.0,
            "popltnVal": null,
            "gdpVal": null,
            "isoWd2NatCd": null,
            "kcskorImpAmt": null,
            "predAmt": null,
            "resnCnt": null
        },
        {
            "baseYr": "2021",
            "mticd": null,
            "itcNatCd": null,
            "natName": null,
            "impAmt": null,
            "expAmt": null,
            "korImpAmt": null,
            "korExpAmt": null,
            "korImpMkshRate": null,
            "impMkshRate": null,
            "impGrowthRate": null,
            "expMkshRate": null,
            "expGrowthRate": null,
            "impMkshRateChngVal": null,
            "impGrowthRateChngVal": null,
            "yr2GrowthRate": null,
            "yr5GrowthRate": null,
            "expEntpCnt": null,
            "impCntryCnt": null,
            "buyerCnt": null,
            "byoffrCnt": null,
            "dataRegDt": null,
            "hscd": null,
            "cmdltNm": null,
            "cmdltParentNm": null,
            "cmdltGrParentNm": null,
            "quCd": null,
            "rank": null,
            "tradeBal": null,
            "baseYm": null,
            "tradeType": null,
            "predRank": null,
            "avgTarifRate": null,
            "korExpsttAmt": null,
            "korExpsttTotalAmt": 799051528.0,
            "popltnVal": null,
            "gdpVal": null,
            "isoWd2NatCd": null,
            "kcskorImpAmt": null,
            "predAmt": null,
            "resnCnt": null
        },
        {
            "baseYr": "2022",
            "mticd": null,
            "itcNatCd": null,
            "natName": null,
            "impAmt": null,
            "expAmt": null,
            "korImpAmt": null,
            "korExpAmt": null,
            "korImpMkshRate": null,
            "impMkshRate": null,
            "impGrowthRate": null,
            "expMkshRate": null,
            "expGrowthRate": null,
            "impMkshRateChngVal": null,
            "impGrowthRateChngVal": null,
            "yr2GrowthRate": null,
            "yr5GrowthRate": null,
            "expEntpCnt": null,
            "impCntryCnt": null,
            "buyerCnt": null,
            "byoffrCnt": null,
            "dataRegDt": null,
            "hscd": null,
            "cmdltNm": null,
            "cmdltParentNm": null,
            "cmdltGrParentNm": null,
            "quCd": null,
            "rank": null,
            "tradeBal": null,
            "baseYm": null,
            "tradeType": null,
            "predRank": null,
            "avgTarifRate": null,
            "korExpsttAmt": null,
            "korExpsttTotalAmt": 1084972494.0,
            "popltnVal": null,
            "gdpVal": null,
            "isoWd2NatCd": null,
            "kcskorImpAmt": null,
            "predAmt": null,
            "resnCnt": null
        }
    ]
}